atelier/__init__.py
atelier/jarbuilder.py
atelier/projects.py
atelier/setup_info.py
atelier/sheller.py
atelier/sphinxconf.py
atelier/test.py
atelier/utils.py
atelier/cli/__init__.py
atelier/cli/foreach.py
atelier/cli/listapps.py
atelier/cli/per_project.py
atelier/invlib/__init__.py
atelier/invlib/ns.py
atelier/invlib/tasks.py
atelier/invlib/utils.py
atelier-1.1.57.dist-info/METADATA
atelier-1.1.57.dist-info/WHEEL
atelier-1.1.57.dist-info/entry_points.txt
atelier-1.1.57.dist-info/licenses/COPYING
atelier-1.1.57.dist-info/RECORD
