Metadata-Version: 2.4
Name: atelier
Version: 1.1.57
Summary: A collection of tools for software artists.
Project-URL: Homepage, https://lino-framework.gitlab.io/atelier
Project-URL: Repository, https://gitlab.com/lino-framework/atelier
Author-email: Rumma & Ko Ltd <info@saffre-rumma.net>, Luc Saffre <luc@saffre-rumma.net>
License:                     GNU AFFERO GENERAL PUBLIC LICENSE
License-File: COPYING
Classifier: Development Status :: 5 - Production/Stable
Classifier: Environment :: Web Environment
Classifier: Intended Audience :: Developers
Classifier: Intended Audience :: System Administrators
Classifier: License :: OSI Approved :: GNU Affero General Public License v3
Classifier: Natural Language :: English
Classifier: Operating System :: OS Independent
Classifier: Programming Language :: Python
Classifier: Programming Language :: Python :: 3
Classifier: Topic :: Database :: Front-Ends
Classifier: Topic :: Software Development :: Libraries :: Application Frameworks
Classifier: Topic :: System :: Installation/Setup
Requires-Python: >=3.8
Requires-Dist: argh
Requires-Dist: babel
Requires-Dist: future
Requires-Dist: gitpython
Requires-Dist: insipid-sphinx-theme
Requires-Dist: invoke
Requires-Dist: pydata-sphinx-theme
Requires-Dist: python-dateutil
Requires-Dist: requests
Requires-Dist: rstgen
Requires-Dist: six
Requires-Dist: sphinx
Requires-Dist: sphinx-design
Requires-Dist: toml
Provides-Extra: dev
Requires-Dist: hatch; extra == 'dev'
Requires-Dist: pytest; extra == 'dev'
Requires-Dist: pytest-cov; extra == 'dev'
Provides-Extra: testing
Requires-Dist: pytest; extra == 'testing'
Requires-Dist: pytest-env; extra == 'testing'
Requires-Dist: pytest-forked; extra == 'testing'
Requires-Dist: pytest-html; extra == 'testing'
